onegov.pdf-0.5.3-py3.6-nspkg.pth
onegov/pdf/.gitignore
onegov/pdf/__init__.py
onegov/pdf/cli.py
onegov/pdf/flowables.py
onegov/pdf/page_functions.py
onegov/pdf/pdf.py
onegov/pdf/signature.py
onegov/pdf/templates.py
onegov/pdf/upgrade.py
onegov/pdf/tests/conftest.py
onegov/pdf/tests/test_pdf.py
onegov/pdf/tests/test_signature.py
onegov/pdf/tests/fixtures/onegov.jpg
onegov/pdf/tests/fixtures/onegov.png
onegov/pdf/tests/fixtures/onegov.svg
onegov.pdf-0.5.3.dist-info/METADATA
onegov.pdf-0.5.3.dist-info/WHEEL
onegov.pdf-0.5.3.dist-info/entry_points.txt
onegov.pdf-0.5.3.dist-info/namespace_packages.txt
onegov.pdf-0.5.3.dist-info/top_level.txt
onegov.pdf-0.5.3.dist-info/RECORD
