Metadata-Version: 2.1
Name: onegov.pdf
Version: 0.5.3
Summary: PDF for OneGov.
Home-page: http://github.com/OneGov/onegov.pdf
Author: Seantis GmbH
Author-email: info@seantis.ch
License: GPLv2
Platform: any
Classifier: Intended Audience :: Developers
Classifier: Programming Language :: Python :: 3 :: Only
Classifier: Programming Language :: Python :: 3.6
Classifier: Programming Language :: Python :: 3.7
Classifier: Topic :: Software Development :: Libraries :: Python Modules
Classifier: License :: OSI Approved :: GNU General Public License v2 (GPLv2)
Requires-Python: >=3.6
Requires-Dist: bleach
Requires-Dist: lxml
Requires-Dist: html5lib
Requires-Dist: onegov.core (>=0.4.0)
Requires-Dist: pdfdocument
Requires-Dist: pdfrw
Requires-Dist: reportlab
Requires-Dist: svglib (>=0.9.0)
Provides-Extra: test
Requires-Dist: coverage ; extra == 'test'
Requires-Dist: onegov-testing ; extra == 'test'
Requires-Dist: pytest ; extra == 'test'
Requires-Dist: PyPDF2 ; extra == 'test'
Requires-Dist: lxml ; extra == 'test'
